cp_measure-0.1.13.dist-info/METADATA
cp_measure-0.1.13.dist-info/WHEEL
cp_measure-0.1.13.dist-info/entry_points.txt
cp_measure-0.1.13.dist-info/licenses/LICENSE
cp_measure/.ruff_cache/.gitignore
cp_measure/.ruff_cache/0.4.4/15091005371779653896
cp_measure/.ruff_cache/0.4.4/4975706593335284859
cp_measure/.ruff_cache/0.4.4/5487261225923883514
cp_measure/.ruff_cache/0.4.4/8463036785068514459
cp_measure/.ruff_cache/CACHEDIR.TAG
cp_measure/bulk.py
cp_measure/core/#%2Aediff-merge%2A#SVfZg1#
cp_measure/core/.pytest_cache/.gitignore
cp_measure/core/.pytest_cache/CACHEDIR.TAG
cp_measure/core/.pytest_cache/README.md
cp_measure/core/.pytest_cache/v/cache/nodeids
cp_measure/core/.pytest_cache/v/cache/stepwise
cp_measure/core/.ruff_cache/.gitignore
cp_measure/core/.ruff_cache/0.4.4/17991247316027556712
cp_measure/core/.ruff_cache/CACHEDIR.TAG
cp_measure/core/measurecolocalization.py
cp_measure/core/measuregranularity.py
cp_measure/core/measureobjectintensity.py
cp_measure/core/measureobjectintensitydistribution.py
cp_measure/core/measureobjectsizeshape.py
cp_measure/core/measuretexture.py
cp_measure/core/utils.py
cp_measure/delme.png
cp_measure/delme2.png
cp_measure/examples.py
cp_measure/multimask/.pytest_cache/.gitignore
cp_measure/multimask/.pytest_cache/CACHEDIR.TAG
cp_measure/multimask/.pytest_cache/README.md
cp_measure/multimask/.pytest_cache/v/cache/nodeids
cp_measure/multimask/.pytest_cache/v/cache/stepwise
cp_measure/multimask/.ruff_cache/.gitignore
cp_measure/multimask/.ruff_cache/0.4.4/13717076724888343098
cp_measure/multimask/.ruff_cache/CACHEDIR.TAG
cp_measure/multimask/measureobjectneighbors.py
cp_measure/multimask/measureobjectoverlap.py
cp_measure/tmp.py
cp_measure/utils.py
cp_measure-0.1.13.dist-info/RECORD
