Metadata-Version: 2.1
Name: cp_measure
Version: 0.1.13
Summary: cp_measure implements CellProfiler measurements in an accessible interface. 
Author: Alan Munoz
Project-URL: Homepage, https://github.com/afermg/cp_measure
Requires-Python: <3.15,>=3.10
Requires-Dist: scikit-image>=0.25
Requires-Dist: scipy>=1.9.1
Requires-Dist: centrosome>=1.3.3
Requires-Dist: numpy>=1.22.1
Requires-Dist: mahotas<2.0.0,>=1.4.13
